iqapy/__init__.py
iqapy-0.0.0.dist-info/LICENSE.md
iqapy-0.0.0.dist-info/METADATA
iqapy-0.0.0.dist-info/WHEEL
iqapy-0.0.0.dist-info/top_level.txt
iqapy-0.0.0.dist-info/RECORD
